{
    "code": 200,
    "message": "success",
    "data": [
        {
            "id": 26,
            "cid": "3300001",
            "goodsName": "扬州炒饭",
            "price": 58.0,
            "selfPrice": 0.0,
            "unit": "碗",
            "typeId": 47,
            "typeName": "主食类",
            "printId": 3,
            "printName": "厨房",
            "propertyIds": "",
            "img": "order-goods/bd3520ee88f74442b6aad5bf5e83f01e.jpeg",
            "description": null,
            "stock": 11092,
            "ableDiscount": 1,
            "ableReturn": 1,
            "isLowConsume": 1,
            "storeDay": null,
            "storeMinCount": null,
            "isWholeStore": null,
            "delayDays": null,
            "maxDelayCount": null,
            "status": 1,
            "propertyList": null
        },
        {
            "id": 13,
            "cid": "3300001",
            "goodsName": "印尼炒饭",
            "price": 58.0,
            "selfPrice": 10.0,
            "unit": "碗",
            "typeId": 47,
            "typeName": "主食类",
            "printId": 3,
            "printName": "厨房",
            "propertyIds": "19,20,21",
            "img": "order-goods/e72898f5f38f4e8da410efee8f318fe1.png",
            "description": "东北大米",
            "stock": 99992,
            "ableDiscount": 0,
            "ableReturn": 1,
            "isLowConsume": 1,
            "storeDay": null,
            "storeMinCount": null,
            "isWholeStore": null,
            "delayDays": null,
            "maxDelayCount": null,
            "status": 1,
            "propertyList": [
                {
                    "id": 19,
                    "cid": "3300001",
                    "propertyName": "大份",
                    "parentId": 18
                },
                {
                    "id": 20,
                    "cid": "3300001",
                    "propertyName": "中份",
                    "parentId": 18
                },
                {
                    "id": 21,
                    "cid": "3300001",
                    "propertyName": "小份",
                    "parentId": 18
                }
            ]
        },
        {
            "id": 161,
            "cid": "3300001",
            "goodsName": "印尼炒饭",
            "price": 58.0,
            "selfPrice": null,
            "unit": "份",
            "typeId": 47,
            "typeName": "主食类",
            "printId": 3,
            "printName": "厨房",
            "propertyIds": "",
            "img": "order-goods/9a09c80e8eb94d3bab5acc2ba4a4c702.png",
            "description": null,
            "stock": 10000,
            "ableDiscount": 1,
            "ableReturn": 1,
            "isLowConsume": 1,
            "storeDay": null,
            "storeMinCount": null,
            "isWholeStore": null,
            "delayDays": null,
            "maxDelayCount": null,
            "status": 1,
            "propertyList": null
        },
        {
            "id": 162,
            "cid": "3300001",
            "goodsName": "扬州炒饭",
            "price": 58.0,
            "selfPrice": null,
            "unit": "份",
            "typeId": 47,
            "typeName": "主食类",
            "printId": 3,
            "printName": "厨房",
            "propertyIds": "",
            "img": "order-goods/0eb4253ca30b4726b7644052132bdb69.jpeg",
            "description": null,
            "stock": 10000,
            "ableDiscount": 1,
            "ableReturn": 1,
            "isLowConsume": 1,
            "storeDay": null,
            "storeMinCount": null,
            "isWholeStore": null,
            "delayDays": null,
            "maxDelayCount": null,
            "status": 1,
            "propertyList": null
        },
        {
            "id": 163,
            "cid": "3300001",
            "goodsName": "时菜/杭椒排骨饭",
            "price": 58.0,
            "selfPrice": null,
            "unit": "份",
            "typeId": 47,
            "typeName": "主食类",
            "printId": 3,
            "printName": "厨房",
            "propertyIds": "",
            "img": "order-goods/f6b02f79de6a455fbbcf5853c9d8f4c4.jpg",
            "description": null,
            "stock": 9999,
            "ableDiscount": 1,
            "ableReturn": 1,
            "isLowConsume": 1,
            "storeDay": null,
            "storeMinCount": null,
            "isWholeStore": null,
            "delayDays": null,
            "maxDelayCount": null,
            "status": 1,
            "propertyList": null
        },
        {
            "id": 164,
            "cid": "3300001",
            "goodsName": "时菜/杭椒牛腩饭",
            "price": 58.0,
            "selfPrice": null,
            "unit": "份",
            "typeId": 47,
            "typeName": "主食类",
            "printId": 3,
            "printName": "厨房",
            "propertyIds": "",
            "img": "order-goods/9cadc5f61c3949129a316c6b41bd3958.jpg",
            "description": null,
            "stock": 10000,
            "ableDiscount": 1,
            "ableReturn": 1,
            "isLowConsume": 1,
            "storeDay": null,
            "storeMinCount": null,
            "isWholeStore": null,
            "delayDays": null,
            "maxDelayCount": null,
            "status": 1,
            "propertyList": null
        },
        {
            "id": 165,
            "cid": "3300001",
            "goodsName": "日式海鲜乌冬面",
            "price": 58.0,
            "selfPrice": null,
            "unit": "份",
            "typeId": 47,
            "typeName": "主食类",
            "printId": 3,
            "printName": "厨房",
            "propertyIds": "",
            "img": "order-goods/3cecd334b29c4e4aa6396d5b606c6717.jpg",
            "description": null,
            "stock": 10000,
            "ableDiscount": 1,
            "ableReturn": 1,
            "isLowConsume": 1,
            "storeDay": null,
            "storeMinCount": null,
            "isWholeStore": null,
            "delayDays": null,
            "maxDelayCount": null,
            "status": 1,
            "propertyList": null
        },
        {
            "id": 166,
            "cid": "3300001",
            "goodsName": "酱鸭泡饭",
            "price": 48.0,
            "selfPrice": null,
            "unit": "份",
            "typeId": 47,
            "typeName": "主食类",
            "printId": 3,
            "printName": "厨房",
            "propertyIds": "",
            "img": "order-goods/7cd99a4ea3e04eb09050551a72fa5232.jpg",
            "description": null,
            "stock": 10000,
            "ableDiscount": 1,
            "ableReturn": 1,
            "isLowConsume": 1,
            "storeDay": null,
            "storeMinCount": null,
            "isWholeStore": null,
            "delayDays": null,
            "maxDelayCount": null,
            "status": 1,
            "propertyList": null
        },
        {
            "id": 167,
            "cid": "3300001",
            "goodsName": "鸭肠剁椒炒饭",
            "price": 48.0,
            "selfPrice": null,
            "unit": "份",
            "typeId": 47,
            "typeName": "主食类",
            "printId": 3,
            "printName": "厨房",
            "propertyIds": "",
            "img": "order-goods/577002983df44859ab157cb7ce401125.jpg",
            "description": null,
            "stock": 10000,
            "ableDiscount": 1,
            "ableReturn": 1,
            "isLowConsume": 1,
            "storeDay": null,
            "storeMinCount": null,
            "isWholeStore": null,
            "delayDays": null,
            "maxDelayCount": null,
            "status": 1,
            "propertyList": null
        },
        {
            "id": 168,
            "cid": "3300001",
            "goodsName": "美味炒米粉",
            "price": 48.0,
            "selfPrice": null,
            "unit": "份",
            "typeId": 47,
            "typeName": "主食类",
            "printId": 3,
            "printName": "厨房",
            "propertyIds": "",
            "img": "order-goods/743c81efcfad4b6eb866ef8db11a66b6.jpg",
            "description": null,
            "stock": 10000,
            "ableDiscount": 1,
            "ableReturn": 1,
            "isLowConsume": 1,
            "storeDay": null,
            "storeMinCount": null,
            "isWholeStore": null,
            "delayDays": null,
            "maxDelayCount": null,
            "status": 1,
            "propertyList": null
        },
        {
            "id": 169,
            "cid": "3300001",
            "goodsName": "排骨面",
            "price": 48.0,
            "selfPrice": null,
            "unit": "份",
            "typeId": 47,
            "typeName": "主食类",
            "printId": 3,
            "printName": "厨房",
            "propertyIds": "",
            "img": "order-goods/a165c10ffc774611b4b3ac07a75435c4.jpg",
            "description": null,
            "stock": 10000,
            "ableDiscount": 1,
            "ableReturn": 1,
            "isLowConsume": 1,
            "storeDay": null,
            "storeMinCount": null,
            "isWholeStore": null,
            "delayDays": null,
            "maxDelayCount": null,
            "status": 1,
            "propertyList": null
        },
        {
            "id": 170,
            "cid": "3300001",
            "goodsName": "牛腩面",
            "price": 48.0,
            "selfPrice": null,
            "unit": "份",
            "typeId": 47,
            "typeName": "主食类",
            "printId": 3,
            "printName": "厨房",
            "propertyIds": "",
            "img": "order-goods/3770e1e14da54ab7be6dacb842a39bbd.jpg",
            "description": null,
            "stock": 10000,
            "ableDiscount": 1,
            "ableReturn": 1,
            "isLowConsume": 1,
            "storeDay": null,
            "storeMinCount": null,
            "isWholeStore": null,
            "delayDays": null,
            "maxDelayCount": null,
            "status": 1,
            "propertyList": null
        },
        {
            "id": 171,
            "cid": "3300001",
            "goodsName": "长寿面",
            "price": 48.0,
            "selfPrice": null,
            "unit": "份",
            "typeId": 47,
            "typeName": "主食类",
            "printId": 3,
            "printName": "厨房",
            "propertyIds": "",
            "img": "order-goods/76ff2739b8834654aa283c54a35931e6.jpg",
            "description": null,
            "stock": 10000,
            "ableDiscount": 1,
            "ableReturn": 1,
            "isLowConsume": 1,
            "storeDay": null,
            "storeMinCount": null,
            "isWholeStore": null,
            "delayDays": null,
            "maxDelayCount": null,
            "status": 1,
            "propertyList": null
        }
    ]
}