{
    "code": 200,
    "message": "success",
    "data": [
        {
            "id": 96,
            "cid": "3300001",
            "goodsName": "普洱茶",
            "price": 38.0,
            "selfPrice": null,
            "unit": "杯",
            "typeId": 50,
            "typeName": "热饮",
            "printId": 6,
            "printName": "吧台出品",
            "propertyIds": "",
            "img": "order-goods/82364b8dfaff4e4d9b76a5c1af856f1c.jpg",
            "description": null,
            "stock": 9995,
            "ableDiscount": 1,
            "ableReturn": 1,
            "isLowConsume": 1,
            "storeDay": null,
            "storeMinCount": null,
            "isWholeStore": null,
            "delayDays": null,
            "maxDelayCount": null,
            "status": 1,
            "propertyList": null
        },
        {
            "id": 97,
            "cid": "3300001",
            "goodsName": "西洋参茶",
            "price": 38.0,
            "selfPrice": null,
            "unit": "杯",
            "typeId": 50,
            "typeName": "热饮",
            "printId": 6,
            "printName": "吧台出品",
            "propertyIds": "",
            "img": "order-goods/05b2f91bd5c4405aa39d230a5a87bda6.jpg",
            "description": null,
            "stock": 9999,
            "ableDiscount": 1,
            "ableReturn": 1,
            "isLowConsume": 1,
            "storeDay": null,
            "storeMinCount": null,
            "isWholeStore": null,
            "delayDays": null,
            "maxDelayCount": null,
            "status": 1,
            "propertyList": null
        },
        {
            "id": 98,
            "cid": "3300001",
            "goodsName": "铁观音",
            "price": 38.0,
            "selfPrice": null,
            "unit": "杯",
            "typeId": 50,
            "typeName": "热饮",
            "printId": 6,
            "printName": "吧台出品",
            "propertyIds": "",
            "img": "order-goods/d25d936994fb403aacec2c8ed11edb04.jpg",
            "description": null,
            "stock": 9999,
            "ableDiscount": 1,
            "ableReturn": 1,
            "isLowConsume": 1,
            "storeDay": null,
            "storeMinCount": null,
            "isWholeStore": null,
            "delayDays": null,
            "maxDelayCount": null,
            "status": 1,
            "propertyList": null
        },
        {
            "id": 99,
            "cid": "3300001",
            "goodsName": "菊花茶",
            "price": 35.0,
            "selfPrice": null,
            "unit": "杯",
            "typeId": 50,
            "typeName": "热饮",
            "printId": 6,
            "printName": "吧台出品",
            "propertyIds": "",
            "img": "order-goods/c4a7df0e1fdc4fd89bb756cb8fcef5d1.jpg",
            "description": null,
            "stock": 9997,
            "ableDiscount": 1,
            "ableReturn": 1,
            "isLowConsume": 1,
            "storeDay": null,
            "storeMinCount": null,
            "isWholeStore": null,
            "delayDays": null,
            "maxDelayCount": null,
            "status": 1,
            "propertyList": null
        },
        {
            "id": 100,
            "cid": "3300001",
            "goodsName": "西湖龙井",
            "price": 35.0,
            "selfPrice": null,
            "unit": "杯",
            "typeId": 50,
            "typeName": "热饮",
            "printId": 6,
            "printName": "吧台出品",
            "propertyIds": "",
            "img": "order-goods/e94d65f50a224f6a8ef42d8c040aa38c.jpg",
            "description": null,
            "stock": 9999,
            "ableDiscount": 1,
            "ableReturn": 1,
            "isLowConsume": 1,
            "storeDay": null,
            "storeMinCount": null,
            "isWholeStore": null,
            "delayDays": null,
            "maxDelayCount": null,
            "status": 1,
            "propertyList": null
        },
        {
            "id": 101,
            "cid": "3300001",
            "goodsName": "冷/热纯牛奶",
            "price": 35.0,
            "selfPrice": null,
            "unit": "杯",
            "typeId": 50,
            "typeName": "热饮",
            "printId": 6,
            "printName": "吧台出品",
            "propertyIds": "",
            "img": "order-goods/7bf9ae0108bb4fc79d27787af8961245.jpg",
            "description": null,
            "stock": 9997,
            "ableDiscount": 1,
            "ableReturn": 1,
            "isLowConsume": 1,
            "storeDay": null,
            "storeMinCount": null,
            "isWholeStore": null,
            "delayDays": null,
            "maxDelayCount": null,
            "status": 1,
            "propertyList": null
        },
        {
            "id": 102,
            "cid": "3300001",
            "goodsName": "冷/热柠檬茶",
            "price": 30.0,
            "selfPrice": null,
            "unit": "杯",
            "typeId": 50,
            "typeName": "热饮",
            "printId": 6,
            "printName": "吧台出品",
            "propertyIds": "",
            "img": "order-goods/2b68648039544d369a9dfdb908f2c824.jpg",
            "description": null,
            "stock": 9995,
            "ableDiscount": 1,
            "ableReturn": 1,
            "isLowConsume": 1,
            "storeDay": null,
            "storeMinCount": null,
            "isWholeStore": null,
            "delayDays": null,
            "maxDelayCount": null,
            "status": 1,
            "propertyList": null
        },
        {
            "id": 103,
            "cid": "3300001",
            "goodsName": "蜂蜜水",
            "price": 30.0,
            "selfPrice": null,
            "unit": "杯",
            "typeId": 50,
            "typeName": "热饮",
            "printId": 6,
            "printName": "吧台出品",
            "propertyIds": "",
            "img": "order-goods/ed566e99a5bb4005a7bdf082dc41a452.jpg",
            "description": null,
            "stock": 9993,
            "ableDiscount": 1,
            "ableReturn": 1,
            "isLowConsume": 1,
            "storeDay": null,
            "storeMinCount": null,
            "isWholeStore": null,
            "delayDays": null,
            "maxDelayCount": null,
            "status": 1,
            "propertyList": null
        },
        {
            "id": 104,
            "cid": "3300001",
            "goodsName": "立顿红茶",
            "price": 30.0,
            "selfPrice": null,
            "unit": "杯",
            "typeId": 50,
            "typeName": "热饮",
            "printId": 6,
            "printName": "吧台出品",
            "propertyIds": "",
            "img": "order-goods/a60781d4097c4a30a7e3b02ac7556f0e.jpg",
            "description": null,
            "stock": 9999,
            "ableDiscount": 1,
            "ableReturn": 1,
            "isLowConsume": 1,
            "storeDay": null,
            "storeMinCount": null,
            "isWholeStore": null,
            "delayDays": null,
            "maxDelayCount": null,
            "status": 1,
            "propertyList": null
        }
    ]
}