{
    "code": 200,
    "message": "success",
    "data": [
        {
            "id": 140,
            "cid": "3300001",
            "goodsName": "香脆黄秋葵",
            "price": 48.0,
            "selfPrice": null,
            "unit": "份",
            "typeId": 45,
            "typeName": "小吃类",
            "printId": 3,
            "printName": "厨房",
            "propertyIds": "",
            "img": "order-goods/2eb65ff097354366a113b70b4ec66c40.jpg",
            "description": null,
            "stock": 9993,
            "ableDiscount": 1,
            "ableReturn": 1,
            "isLowConsume": 1,
            "storeDay": null,
            "storeMinCount": null,
            "isWholeStore": null,
            "delayDays": null,
            "maxDelayCount": null,
            "status": 1,
            "propertyList": null
        },
        {
            "id": 141,
            "cid": "3300001",
            "goodsName": "美味藕尖",
            "price": 38.0,
            "selfPrice": null,
            "unit": "份",
            "typeId": 45,
            "typeName": "小吃类",
            "printId": 3,
            "printName": "厨房",
            "propertyIds": "",
            "img": "order-goods/613a14ba8a3a4a71b3d6d2ff53069a75.jpg",
            "description": null,
            "stock": 9997,
            "ableDiscount": 1,
            "ableReturn": 1,
            "isLowConsume": 1,
            "storeDay": null,
            "storeMinCount": null,
            "isWholeStore": null,
            "delayDays": null,
            "maxDelayCount": null,
            "status": 1,
            "propertyList": null
        },
        {
            "id": 142,
            "cid": "3300001",
            "goodsName": "红油笋尖",
            "price": 38.0,
            "selfPrice": null,
            "unit": "份",
            "typeId": 45,
            "typeName": "小吃类",
            "printId": 3,
            "printName": "厨房",
            "propertyIds": "",
            "img": "order-goods/b7540f9133b545c38413b2b562dfe7d0.jpg",
            "description": null,
            "stock": 9999,
            "ableDiscount": 1,
            "ableReturn": 1,
            "isLowConsume": 1,
            "storeDay": null,
            "storeMinCount": null,
            "isWholeStore": null,
            "delayDays": null,
            "maxDelayCount": null,
            "status": 1,
            "propertyList": null
        },
        {
            "id": 143,
            "cid": "3300001",
            "goodsName": "凉拌豆干",
            "price": 38.0,
            "selfPrice": null,
            "unit": "份",
            "typeId": 45,
            "typeName": "小吃类",
            "printId": 3,
            "printName": "厨房",
            "propertyIds": "",
            "img": "order-goods/55429c54215d43ed99e597a04920933c.jpg",
            "description": null,
            "stock": 9999,
            "ableDiscount": 1,
            "ableReturn": 1,
            "isLowConsume": 1,
            "storeDay": null,
            "storeMinCount": null,
            "isWholeStore": null,
            "delayDays": null,
            "maxDelayCount": null,
            "status": 1,
            "propertyList": null
        },
        {
            "id": 144,
            "cid": "3300001",
            "goodsName": "凉拌海带结",
            "price": 38.0,
            "selfPrice": null,
            "unit": "份",
            "typeId": 45,
            "typeName": "小吃类",
            "printId": 3,
            "printName": "厨房",
            "propertyIds": "",
            "img": "order-goods/bca47ceb19d84e48aa5e64b03081d690.jpg",
            "description": null,
            "stock": 10000,
            "ableDiscount": 1,
            "ableReturn": 1,
            "isLowConsume": 1,
            "storeDay": null,
            "storeMinCount": null,
            "isWholeStore": null,
            "delayDays": null,
            "maxDelayCount": null,
            "status": 1,
            "propertyList": null
        },
        {
            "id": 145,
            "cid": "3300001",
            "goodsName": "凉拌/沾酱黄瓜",
            "price": 38.0,
            "selfPrice": null,
            "unit": "份",
            "typeId": 45,
            "typeName": "小吃类",
            "printId": 3,
            "printName": "厨房",
            "propertyIds": "",
            "img": "order-goods/37f054c28177468eb7273f37d2844011.jpg",
            "description": null,
            "stock": 10000,
            "ableDiscount": 1,
            "ableReturn": 1,
            "isLowConsume": 1,
            "storeDay": null,
            "storeMinCount": null,
            "isWholeStore": null,
            "delayDays": null,
            "maxDelayCount": null,
            "status": 1,
            "propertyList": null
        },
        {
            "id": 146,
            "cid": "3300001",
            "goodsName": "盐水花生",
            "price": 38.0,
            "selfPrice": null,
            "unit": "份",
            "typeId": 45,
            "typeName": "小吃类",
            "printId": 3,
            "printName": "厨房",
            "propertyIds": "",
            "img": "order-goods/88b077f9638b49d89fefd96ed9c2c8fa.gif",
            "description": null,
            "stock": 10000,
            "ableDiscount": 1,
            "ableReturn": 1,
            "isLowConsume": 1,
            "storeDay": null,
            "storeMinCount": null,
            "isWholeStore": null,
            "delayDays": null,
            "maxDelayCount": null,
            "status": 1,
            "propertyList": null
        },
        {
            "id": 147,
            "cid": "3300001",
            "goodsName": "盐水毛豆",
            "price": 38.0,
            "selfPrice": null,
            "unit": "份",
            "typeId": 45,
            "typeName": "小吃类",
            "printId": 3,
            "printName": "厨房",
            "propertyIds": "",
            "img": "order-goods/d4fed498cfd6471cb8a2f6e281bce252.jpg",
            "description": null,
            "stock": 10000,
            "ableDiscount": 1,
            "ableReturn": 1,
            "isLowConsume": 1,
            "storeDay": null,
            "storeMinCount": null,
            "isWholeStore": null,
            "delayDays": null,
            "maxDelayCount": null,
            "status": 1,
            "propertyList": null
        },
        {
            "id": 148,
            "cid": "3300001",
            "goodsName": "香辣豆腐干",
            "price": 38.0,
            "selfPrice": null,
            "unit": "份",
            "typeId": 45,
            "typeName": "小吃类",
            "printId": 3,
            "printName": "厨房",
            "propertyIds": "",
            "img": "order-goods/6542a4f8f65640b3be191c282230bca3.jpg",
            "description": null,
            "stock": 10000,
            "ableDiscount": 1,
            "ableReturn": 1,
            "isLowConsume": 1,
            "storeDay": null,
            "storeMinCount": null,
            "isWholeStore": null,
            "delayDays": null,
            "maxDelayCount": null,
            "status": 1,
            "propertyList": null
        },
        {
            "id": 149,
            "cid": "3300001",
            "goodsName": "麻辣藕片",
            "price": 38.0,
            "selfPrice": null,
            "unit": "份",
            "typeId": 45,
            "typeName": "小吃类",
            "printId": 3,
            "printName": "厨房",
            "propertyIds": "",
            "img": "order-goods/584212f865ec46d598a5862d86771cf6.jpg",
            "description": null,
            "stock": 10000,
            "ableDiscount": 1,
            "ableReturn": 1,
            "isLowConsume": 1,
            "storeDay": null,
            "storeMinCount": null,
            "isWholeStore": null,
            "delayDays": null,
            "maxDelayCount": null,
            "status": 1,
            "propertyList": null
        },
        {
            "id": 150,
            "cid": "3300001",
            "goodsName": "手撕笋",
            "price": 38.0,
            "selfPrice": null,
            "unit": "份",
            "typeId": 45,
            "typeName": "小吃类",
            "printId": 3,
            "printName": "厨房",
            "propertyIds": "",
            "img": "order-goods/72c86fc0c0154379b41bb519e5ad0f50.jpg",
            "description": null,
            "stock": 10000,
            "ableDiscount": 1,
            "ableReturn": 1,
            "isLowConsume": 1,
            "storeDay": null,
            "storeMinCount": null,
            "isWholeStore": null,
            "delayDays": null,
            "maxDelayCount": null,
            "status": 1,
            "propertyList": null
        },
        {
            "id": 151,
            "cid": "3300001",
            "goodsName": "一品蛋酥",
            "price": 38.0,
            "selfPrice": null,
            "unit": "份",
            "typeId": 45,
            "typeName": "小吃类",
            "printId": 3,
            "printName": "厨房",
            "propertyIds": "",
            "img": "order-goods/e6141b9f991b418f9189fd937585fd3a.jpg",
            "description": null,
            "stock": 10000,
            "ableDiscount": 1,
            "ableReturn": 1,
            "isLowConsume": 1,
            "storeDay": null,
            "storeMinCount": null,
            "isWholeStore": null,
            "delayDays": null,
            "maxDelayCount": null,
            "status": 1,
            "propertyList": null
        },
        {
            "id": 152,
            "cid": "3300001",
            "goodsName": "凉拌木耳",
            "price": 38.0,
            "selfPrice": null,
            "unit": "份",
            "typeId": 45,
            "typeName": "小吃类",
            "printId": 3,
            "printName": "厨房",
            "propertyIds": "",
            "img": "order-goods/c42b66e6588c494c845a54632dc4b149.jpg",
            "description": null,
            "stock": 10000,
            "ableDiscount": 1,
            "ableReturn": 1,
            "isLowConsume": 1,
            "storeDay": null,
            "storeMinCount": null,
            "isWholeStore": null,
            "delayDays": null,
            "maxDelayCount": null,
            "status": 1,
            "propertyList": null
        },
        {
            "id": 153,
            "cid": "3300001",
            "goodsName": "爽口榨菜",
            "price": 28.0,
            "selfPrice": null,
            "unit": "份",
            "typeId": 45,
            "typeName": "小吃类",
            "printId": 3,
            "printName": "厨房",
            "propertyIds": "",
            "img": "order-goods/185e7c762feb4042a755d1c554c29f55.jpg",
            "description": null,
            "stock": 10000,
            "ableDiscount": 1,
            "ableReturn": 1,
            "isLowConsume": 1,
            "storeDay": null,
            "storeMinCount": null,
            "isWholeStore": null,
            "delayDays": null,
            "maxDelayCount": null,
            "status": 1,
            "propertyList": null
        },
        {
            "id": 154,
            "cid": "3300001",
            "goodsName": "兰花豆",
            "price": 28.0,
            "selfPrice": null,
            "unit": "份",
            "typeId": 45,
            "typeName": "小吃类",
            "printId": 3,
            "printName": "厨房",
            "propertyIds": "",
            "img": "order-goods/8cb0e511a0854bd296d63f0cf456ed68.jpg",
            "description": null,
            "stock": 10000,
            "ableDiscount": 1,
            "ableReturn": 1,
            "isLowConsume": 1,
            "storeDay": null,
            "storeMinCount": null,
            "isWholeStore": null,
            "delayDays": null,
            "maxDelayCount": null,
            "status": 1,
            "propertyList": null
        }
    ]
}